klipper_beacon/__init__.py
klipper_beacon/beacon.py
klipper_beacon-1.0.5.dist-info/LICENSE
klipper_beacon-1.0.5.dist-info/METADATA
klipper_beacon-1.0.5.dist-info/WHEEL
klipper_beacon-1.0.5.dist-info/top_level.txt
klipper_beacon-1.0.5.dist-info/RECORD
